cdd/__init__.py
cdd/cdd.py
cdd/directories.py
cdd/jsonfile.py
cdd-0.1.12.data/scripts/cdd-bash-function.sh
cdd-0.1.12.dist-info/DESCRIPTION.rst
cdd-0.1.12.dist-info/METADATA
cdd-0.1.12.dist-info/RECORD
cdd-0.1.12.dist-info/WHEEL
cdd-0.1.12.dist-info/entry_points.txt
cdd-0.1.12.dist-info/metadata.json
cdd-0.1.12.dist-info/top_level.txt
