Metadata-Version: 2.0
Name: cdd
Version: 0.1.12
Summary: improved file system navigation with cd
Home-page: https://github.com/daltonserey/cdd
Author: Dalton Serey
Author-email: daltonserey@gmail.com
License: GNU Affero General Public License v3
Platform: UNKNOWN
